rindex/__init__.py
rindex/c_rindex.cp310-win_amd64.pyd
rindex/c_rindex.pyx
rindex/py.typed
rindex/pypy_rindex.py
rindex/rindex.py
rindex-1.2.0.dist-info/licenses/LICENSE
rindex-1.2.0.dist-info/METADATA
rindex-1.2.0.dist-info/WHEEL
rindex-1.2.0.dist-info/top_level.txt
rindex-1.2.0.dist-info/RECORD
