Metadata-Version: 2.4
Name: rindex
Version: 1.2.0
Summary: rindex() function for sequences
Author: Sóla Lusøt
License-Expression: MIT
Project-URL: Repository, https://github.com/solaluset/rindex
Requires-Python: >=3.9
License-File: LICENSE
Dynamic: license-file
